{
  "category": "stacked-lists",
  "variant": "narrow-with-sticky-headings",
  "files": {
    "index.ts": "/*\n\tInstalled from https://ui.angular-material.dev/\n\tUpdate this file using `npx @ngm-dev/cli update stacked-lists/narrow-with-sticky-headings`\n*/\n\nexport * from './narrow-with-sticky-headings.component';\nexport * from './narrow-with-sticky-headings.model';\n",
    "narrow-with-sticky-headings.component.html": "<!--\n\tInstalled from https://ui.angular-material.dev/\n\tUpdate this file using `npx @ngm-dev/cli update stacked-lists/narrow-with-sticky-headings`\n-->\n\n<div class=\"max-w-lg mx-auto\">\n  <mat-list class=\"max-h-[39rem] overflow-y-auto py-0!\">\n    @for (group of contacts; track group.id) {\n    <h3\n      matSubheader\n      class=\"sticky top-0 bg-surface-container-high m-0! p-2 z-10\"\n    >\n      {{ group.label }}\n    </h3>\n    @for (contact of group.items; track contact.id; let last = $last) {\n    <mat-list-item>\n      <img [src]=\"contact.imageUrl\" matListItemAvatar class=\"rounded-full\" />\n      <span matListItemTitle> {{ contact.name }} </span>\n      <span matListItemLine> {{ contact.email }} </span>\n    </mat-list-item>\n    @if (!last) {\n    <mat-divider />\n    } } }\n  </mat-list>\n</div>\n",
    "narrow-with-sticky-headings.component.scss": "/*\n\tInstalled from https://ui.angular-material.dev/\n\tUpdate this file using `npx @ngm-dev/cli update stacked-lists/narrow-with-sticky-headings`\n*/\n\n@use '@angular/material' as mat;\n\n:host {\n  @include mat.list-overrides(\n    (\n      list-item-supporting-text-color: color-mix(\n          in srgb,\n          var(--mat-sys-on-surface),\n          transparent 50%\n        ),\n    )\n  );\n  @include mat.divider-overrides(\n    (\n      color: var(--mat-sys-outline-variant),\n    )\n  );\n}\n",
    "narrow-with-sticky-headings.component.ts": "/*\n\tInstalled from https://ui.angular-material.dev/\n\tUpdate this file using `npx @ngm-dev/cli update stacked-lists/narrow-with-sticky-headings`\n*/\n\nimport { Component } from '@angular/core';\nimport { MatListModule } from '@angular/material/list';\nimport { MatDividerModule } from '@angular/material/divider';\nimport { narrowWithStickyHeadingsContacts } from './narrow-with-sticky-headings.model';\n\n@Component({\n  selector: 'ngm-dev-block-narrow-with-sticky-headings',\n  templateUrl: './narrow-with-sticky-headings.component.html',\n  styleUrls: ['./narrow-with-sticky-headings.component.scss'],\n  imports: [MatListModule, MatDividerModule],\n})\nexport class NarrowWithStickyHeadingsComponent {\n  contacts = narrowWithStickyHeadingsContacts;\n}\n",
    "narrow-with-sticky-headings.model.ts": "/*\n\tInstalled from https://ui.angular-material.dev/\n\tUpdate this file using `npx @ngm-dev/cli update stacked-lists/narrow-with-sticky-headings`\n*/\n\nexport type NarrowWithStickyHeadingsContact = {\n  label: string;\n  id: string;\n  items: {\n    id: string;\n    name: string;\n    email: string;\n    imageUrl: string;\n  }[];\n};\n\nexport const narrowWithStickyHeadingsContacts: NarrowWithStickyHeadingsContact[] =\n  [\n    {\n      id: '1',\n      label: 'Group 1',\n      items: [\n        {\n          id: '1',\n          name: 'Leslie Alexander',\n          email: 'leslie.alexander@example.com',\n          imageUrl: 'https://i.pravatar.cc/150?img=1',\n        },\n        {\n          id: '2',\n          name: 'Michael Foster',\n          email: 'michael.foster@example.com',\n          imageUrl: 'https://i.pravatar.cc/150?img=2',\n        },\n        {\n          id: '3',\n          name: 'Dries Vincent',\n          email: 'dries.vincent@example.com',\n          imageUrl: 'https://i.pravatar.cc/150?img=3',\n        },\n        {\n          id: '4',\n          name: 'Lindsay Walton',\n          email: 'lindsay.walton@example.com',\n          imageUrl: 'https://i.pravatar.cc/150?img=4',\n        },\n      ],\n    },\n    {\n      id: '2',\n      label: 'Group 2',\n      items: [\n        {\n          id: '5',\n          name: 'Courtney Henry',\n          email: 'courtney.henry@example.com',\n          imageUrl: 'https://i.pravatar.cc/150?img=5',\n        },\n        {\n          id: '6',\n          name: 'Tom Cook',\n          email: 'tom.cook@example.com',\n          imageUrl: 'https://i.pravatar.cc/150?img=6',\n        },\n        {\n          id: '7',\n          name: 'Trevor Hansen',\n          email: 'trevor.hansen@example.com',\n          imageUrl: 'https://i.pravatar.cc/150?img=7',\n        },\n        {\n          id: '8',\n          name: 'Trevor Hansen',\n          email: 'trevor.hansen@example.com',\n          imageUrl: 'https://i.pravatar.cc/150?img=8',\n        },\n      ],\n    },\n    {\n      id: '3',\n      label: 'Group 3',\n      items: [\n        {\n          id: '9',\n          name: 'Mike Crush',\n          email: 'mike.crush@example.com',\n          imageUrl: 'https://i.pravatar.cc/150?img=9',\n        },\n        {\n          id: '10',\n          name: 'John Doe',\n          email: 'john.doe@example.com',\n          imageUrl: 'https://i.pravatar.cc/150?img=10',\n        },\n        {\n          id: '11',\n          name: 'Jane Doe',\n          email: 'jane.doe@example.com',\n          imageUrl: 'https://i.pravatar.cc/150?img=11',\n        },\n        {\n          id: '12',\n          name: 'John Smith',\n          email: 'john.smith@example.com',\n          imageUrl: 'https://i.pravatar.cc/150?img=12',\n        },\n      ],\n    },\n    {\n      id: '4',\n      label: 'Group 4',\n      items: [\n        {\n          id: '13',\n          name: 'Jane Smith',\n          email: 'jane.smith@example.com',\n          imageUrl: 'https://i.pravatar.cc/150?img=13',\n        },\n        {\n          id: '14',\n          name: 'Kira Smith',\n          email: 'kira.smith@example.com',\n          imageUrl: 'https://i.pravatar.cc/150?img=14',\n        },\n        {\n          id: '15',\n          name: 'Ophelia Smith',\n          email: 'ophelia.smith@example.com',\n          imageUrl: 'https://i.pravatar.cc/150?img=15',\n        },\n        {\n          id: '16',\n          name: 'Uta Smith',\n          email: 'uta.smith@example.com',\n          imageUrl: 'https://i.pravatar.cc/150?img=16',\n        },\n      ],\n    },\n    {\n      id: '5',\n      label: 'Group 5',\n      items: [\n        {\n          id: '17',\n          name: 'Courtney Henry',\n          email: 'courtney.henry@example.com',\n          imageUrl: 'https://i.pravatar.cc/150?img=17',\n        },\n        {\n          id: '18',\n          name: 'Vicky Smith',\n          email: 'vicky.smith@example.com',\n          imageUrl: 'https://i.pravatar.cc/150?img=18',\n        },\n        {\n          id: '19',\n          name: 'Wendy Smith',\n          email: 'wendy.smith@example.com',\n          imageUrl: 'https://i.pravatar.cc/150?img=19',\n        },\n        {\n          id: '20',\n          name: 'Xavier Smith',\n          email: 'xavier.smith@example.com',\n          imageUrl: 'https://i.pravatar.cc/150?img=20',\n        },\n      ],\n    },\n    {\n      id: '6',\n      label: 'Group 6',\n      items: [\n        {\n          id: '21',\n          name: 'Yvonne Smith',\n          email: 'yvonne.smith@example.com',\n          imageUrl: 'https://i.pravatar.cc/150?img=21',\n        },\n        {\n          id: '22',\n          name: 'Zara Smith',\n          email: 'zara.smith@example.com',\n          imageUrl: 'https://i.pravatar.cc/150?img=22',\n        },\n        {\n          id: '23',\n          name: 'Kris Kringle',\n          email: 'kris.kringle@example.com',\n          imageUrl: 'https://i.pravatar.cc/150?img=23',\n        },\n        {\n          id: '24',\n          name: 'Santa Claus',\n          email: 'santa.claus@example.com',\n          imageUrl: 'https://i.pravatar.cc/150?img=24',\n        },\n      ],\n    },\n  ];\n"
  }
}